RFXtrx/__init__.py
RFXtrx/lowlevel.py
pyRFXtrx_tipi85-0.25.9.dist-info/COPYING.txt
pyRFXtrx_tipi85-0.25.9.dist-info/METADATA
pyRFXtrx_tipi85-0.25.9.dist-info/WHEEL
pyRFXtrx_tipi85-0.25.9.dist-info/top_level.txt
pyRFXtrx_tipi85-0.25.9.dist-info/RECORD
