Metadata-Version: 2.1
Name: pyRFXtrx-tipi85
Version: 0.25.9
Summary: a library to communicate with the RFXtrx family of devices
Home-page: https://github.com/tipi85/pyRFXtrx
Author: Edwin Woudt
Author-email: edwin@woudt.nl
License: UNKNOWN
Platform: UNKNOWN
Classifier: Development Status :: 3 - Alpha
Classifier: Environment :: Other Environment
Classifier: Intended Audience :: Developers
Classifier: License :: OSI Approved :: GNU Lesser General Public License v3 or later (LGPLv3+)
Classifier: Operating System :: OS Independent
Classifier: Programming Language :: Python
Classifier: Topic :: Home Automation
Classifier: Topic :: Software Development :: Libraries :: Python Modules
Requires-Dist: pyserial (>=2.7)
